gesttalt-0.7.9.dist-info/WHEEL
gesttalt-0.7.9.dist-info/licenses/LICENSE
gesttalt-0.7.9.dist-info/top_level.txt
gesttalt-0.7.9.dist-info/METADATA
gesttalt/lib/libgesttalt_ffi.so
gesttalt/core.py
gesttalt/__init__.py
gesttalt-0.7.9.dist-info/RECORD
