Metadata-Version: 2.4
Name: gesttalt
Version: 0.7.9
Summary: A universal OAuth2.0 client written in Zig concurrency-ready
Author-email: Pedro Pinera Buendia <pedro@ppinera.es>
License: MIT
Project-URL: Homepage, https://github.com/pepicrft/gesttalt
Project-URL: Repository, https://github.com/pepicrft/gesttalt
Project-URL: Issues, https://github.com/pepicrft/gesttalt/issues
Keywords: gesttalt,snippets,crud,zig,ffi
Classifier: Development Status :: 3 - Alpha
Classifier: Intended Audience :: Developers
Classifier: License :: OSI Approved :: MIT License
Classifier: Programming Language :: Python :: 3
Classifier: Programming Language :: Python :: 3.8
Classifier: Programming Language :: Python :: 3.9
Classifier: Programming Language :: Python :: 3.10
Classifier: Programming Language :: Python :: 3.11
Classifier: Programming Language :: Python :: 3.12
Requires-Python: >=3.8
License-File: LICENSE
Provides-Extra: dev
Requires-Dist: pytest>=7.0; extra == "dev"
Dynamic: license-file
